fin68/__init__.py
fin68/_core/__init__.py
fin68/_version.py
fin68/auth/__init__.py
fin68/auth/api_key.py
fin68/clients/__init__.py
fin68/clients/base.py
fin68/clients/eod/MarketEod.py
fin68/clients/eod/SectorEod.py
fin68/clients/eod/StockEod.py
fin68/clients/eod/__init__.py
fin68/clients/eod/helper.py
fin68/clients/eod/icb_types.py
fin68/clients/eod/investor/MarketInvestor.py
fin68/clients/eod/investor/SectorInvestor.py
fin68/clients/eod/investor/StockInvestor.py
fin68/clients/eod/investor/__init__.py
fin68/clients/eod/investor/investor.py
fin68/clients/eod_main.py
fin68/clients/financials.py
fin68/clients/index.py
fin68/clients/info.py
fin68/clients/intraday/DerivativeIntraday.py
fin68/clients/intraday/MarketIntraday.py
fin68/clients/intraday/StockIntraday.py
fin68/clients/intraday/__init__.py
fin68/clients/intraday/helper.py
fin68/clients/intraday_main.py
fin68/clients/reporting/__init__.py
fin68/clients/reporting/helper.py
fin68/clients/reporting/reporting_main.py
fin68/clients/reporting/types.py
fin68/config.py
fin68/exceptions.py
fin68/models/__init__.py
fin68/models/base.py
fin68/models/eod.py
fin68/models/financials.py
fin68/models/index.py
fin68/models/meta.py
fin68/py.typed
fin68/transport/__init__.py
fin68/transport/cache.py
fin68/transport/http.py
fin68/transport/rate_limiter.py
fin68/types.py
fin68/utils/__init__.py
fin68/utils/_validate_date_eod.py
fin68/utils/convert.py
fin68/utils/pagination.py
fin68/utils/time.py
fin68/validators.py
fin68-0.1.11.dist-info/METADATA
fin68-0.1.11.dist-info/RECORD
fin68-0.1.11.dist-info/WHEEL
fin68-0.1.11.dist-info/licenses/LICENSE
fin68-0.1.11.dist-info/top_level.txt
private_core/__init__.py
private_core/auth_core.cpython-311-darwin.so
private_core/cache_core.cpython-311-darwin.so
private_core/cache_mixin.cpython-311-darwin.so
private_core/cache_policy.cpython-311-darwin.so
private_core/eod_core.cpython-311-darwin.so
private_core/financials_core.cpython-311-darwin.so
private_core/helpers.cpython-311-darwin.so
private_core/http_core.cpython-311-darwin.so
private_core/index_core.cpython-311-darwin.so
